swiftencrypt/__init__.py
swiftencrypt/swiftencrypt.py
swiftencrypt-1.0.0.dist-info/METADATA
swiftencrypt-1.0.0.dist-info/WHEEL
swiftencrypt-1.0.0.dist-info/licenses/LICENSE
swiftencrypt-1.0.0.dist-info/RECORD
