Metadata-Version: 2.4
Name: swiftencrypt
Version: 1.0.0
Summary: A simple way to handle basic data encryption.
Project-URL: Homepage, https://github.com/SeanYeatts/swiftencrypt
Author: Sean Yeatts
License: MIT License
License-File: LICENSE
Classifier: License :: OSI Approved :: MIT License
Classifier: Operating System :: Microsoft :: Windows
Classifier: Programming Language :: Python :: 3
Requires-Python: >=3.8
Requires-Dist: cryptography
